sbomgrader-0.2.5.dist-info/METADATA
sbomgrader-0.2.5.dist-info/WHEEL
sbomgrader-0.2.5.dist-info/entry_points.txt
sbomgrader-0.2.5.dist-info/licenses/LICENSE
sbomgrader/__init__.py
sbomgrader/__main__.py
sbomgrader/cookbooks/README.md
sbomgrader/cookbooks/generic_build.yml
sbomgrader/cookbooks/generic_release.yml
sbomgrader/cookbooks/image_build.yml
sbomgrader/cookbooks/image_index_build.yml
sbomgrader/cookbooks/image_index_release.yml
sbomgrader/cookbooks/image_release.yml
sbomgrader/cookbooks/product.yml
sbomgrader/cookbooks/rpm_build.yml
sbomgrader/cookbooks/rpm_release.yml
sbomgrader/cookbooks/schema/cookbook_schema.yml
sbomgrader/core/__init__.py
sbomgrader/core/cached_python_loader.py
sbomgrader/core/definitions.py
sbomgrader/core/documents.py
sbomgrader/core/enums.py
sbomgrader/core/field_resolve.py
sbomgrader/core/formats.py
sbomgrader/core/logging.py
sbomgrader/core/utils.py
sbomgrader/formats/README.md
sbomgrader/formats/formats.yml
sbomgrader/formats/schema/formats_schema.yml
sbomgrader/grade/__init__.py
sbomgrader/grade/choose_cookbooks.py
sbomgrader/grade/cookbook_bundles.py
sbomgrader/grade/cookbooks.py
sbomgrader/grade/rule_loader.py
sbomgrader/grade/rules.py
sbomgrader/rulesets/README.md
sbomgrader/rulesets/general.yml
sbomgrader/rulesets/implementations/general/cdx16.py
sbomgrader/rulesets/implementations/general/spdx23.py
sbomgrader/rulesets/implementations/specific/cdx16.py
sbomgrader/rulesets/implementations/specific/spdx23.py
sbomgrader/rulesets/schema/rule_schema.yml
sbomgrader/rulesets/specific.yml
sbomgrader/translate/__init__.py
sbomgrader/translate/choose_map.py
sbomgrader/translate/prune.py
sbomgrader/translate/translation_map.py
sbomgrader/translation_maps/README.md
sbomgrader/translation_maps/postprocessing/README.md
sbomgrader/translation_maps/postprocessing/red_hat_spdx23_cdx16/cdx16.py
sbomgrader/translation_maps/postprocessing/red_hat_spdx23_cdx16/spdx23.py
sbomgrader/translation_maps/preprocessing/README.md
sbomgrader/translation_maps/preprocessing/red_hat_spdx23_cdx16/cdx16.py
sbomgrader/translation_maps/red_hat_spdx23_cdx16.yml
sbomgrader-0.2.5.dist-info/RECORD
