Metadata-Version: 2.1
Name: sbomgrader
Version: 0.2.5
Summary: SBOM Grader
Author-Email: mszymutk <mszymutk@redhat.com>
License: MIT
Requires-Python: >=3.12
Requires-Dist: jsonschema>=4.23.0
Requires-Dist: pyyaml>=6.0.2
Requires-Dist: spdx-tools>=0.8.3
Requires-Dist: packageurl-python>=0.16.0
Requires-Dist: cyclonedx-python-lib>=8.5.0
Requires-Dist: rich>=13.9.4
Requires-Dist: jinja2>=3.1.5
